treblle/__init__.py
treblle/middleware.py
treblle-2.0.6.dist-info/licenses/LICENSE
treblle-2.0.6.dist-info/licenses/LICENSE.md
treblle-2.0.6.dist-info/METADATA
treblle-2.0.6.dist-info/WHEEL
treblle-2.0.6.dist-info/top_level.txt
treblle-2.0.6.dist-info/RECORD
