Metadata-Version: 2.4
Name: treblle
Version: 2.0.6
Summary: Treblle SDK for Django - Production-ready API monitoring and intelligence platform
Home-page: https://github.com/Treblle/treblle-python
Author: Treblle
Author-email: Treblle <support@treblle.com>
Maintainer-email: Treblle <support@treblle.com>
License-Expression: MIT
Project-URL: Homepage, https://treblle.com
Project-URL: Documentation, https://docs.treblle.com/en/integrations/django
Project-URL: Repository, https://github.com/Treblle/treblle-python
Project-URL: Bug Reports, https://github.com/Treblle/treblle-python/issues
Project-URL: Changelog, https://github.com/Treblle/treblle-python/releases
Keywords: treblle,api,monitoring,django,middleware,observability,analytics,intelligence,devops,production,thread-safe
Classifier: Development Status :: 5 - Production/Stable
Classifier: Intended Audience :: Developers
Classifier: Programming Language :: Python :: 3
Classifier: Programming Language :: Python :: 3.7
Classifier: Programming Language :: Python :: 3.8
Classifier: Programming Language :: Python :: 3.9
Classifier: Programming Language :: Python :: 3.10
Classifier: Programming Language :: Python :: 3.11
Classifier: Programming Language :: Python :: 3.12
Classifier: Framework :: Django
Classifier: Framework :: Django :: 2.2
Classifier: Framework :: Django :: 3.0
Classifier: Framework :: Django :: 3.1
Classifier: Framework :: Django :: 3.2
Classifier: Framework :: Django :: 4.0
Classifier: Framework :: Django :: 4.1
Classifier: Framework :: Django :: 4.2
Classifier: Framework :: Django :: 5.0
Classifier: Framework :: Django :: 5.1
Classifier: Topic :: Software Development :: Libraries :: Python Modules
Classifier: Topic :: Internet :: WWW/HTTP :: HTTP Servers
Classifier: Topic :: System :: Monitoring
Requires-Python: >=3.7
License-File: LICENSE
License-File: LICENSE.md
Requires-Dist: requests>=2.25.0
Requires-Dist: Django>=2.2
Dynamic: author
Dynamic: home-page
Dynamic: license-file
Dynamic: requires-python
